[{"link":"https:\/\/arb-memes.com\/user\/uploads\/img\/0s_ps-20210321-0001.jpg"},{"link":"https:\/\/arb-memes.com\/user\/uploads\/img\/0s_ps-20210321-0002.jpg"},{"link":"https:\/\/arb-memes.com\/user\/uploads\/img\/0s_ps-20210321-0003.jpg"},{"link":"https:\/\/arb-memes.com\/user\/uploads\/img\/3al.5afif-20210321-0001.jpg"},{"link":"https:\/\/arb-memes.com\/user\/uploads\/img\/3al.5afif-20210321-0002.jpg"},{"link":"https:\/\/arb-memes.com\/user\/uploads\/img\/05bt-20210321-0004.jpg"},{"link":"https:\/\/arb-memes.com\/user\/uploads\/img\/05bt-20210321-0007.jpg"},{"link":"https:\/\/arb-memes.com\/user\/uploads\/img\/05bt-20210321-0010.jpg"},{"link":"https:\/\/arb-memes.com\/user\/uploads\/img\/7e.i-20210321-0001.jpg"},{"link":"https:\/\/arb-memes.com\/user\/uploads\/img\/7madaa.io-20210321-0001.jpg"},{"link":"https:\/\/arb-memes.com\/user\/uploads\/img\/7ob_51-20210401-0001.jpg"},{"link":"https:\/\/arb-memes.com\/user\/uploads\/img\/7ob_51-20210404-0001.jpg"},{"link":"https:\/\/arb-memes.com\/user\/uploads\/img\/44de_-20210321-0001.jpg"},{"link":"https:\/\/arb-memes.com\/user\/uploads\/img\/44de_-20210321-0002.jpg"},{"link":"https:\/\/arb-memes.com\/user\/uploads\/img\/44de_-20210330-0001.jpg"},{"link":"https:\/\/arb-memes.com\/user\/uploads\/img\/44de_-20210401-0003.jpg"},{"link":"https:\/\/arb-memes.com\/user\/uploads\/img\/44de_-20210404-0002.jpg"},{"link":"https:\/\/arb-memes.com\/user\/uploads\/img\/44de_-20210404-0006.jpg"},{"link":"https:\/\/arb-memes.com\/user\/uploads\/img\/44de_-20210404-0007.jpg"},{"link":"https:\/\/arb-memes.com\/user\/uploads\/img\/44de_-20210411-0001.jpg"},{"link":"https:\/\/arb-memes.com\/user\/uploads\/img\/44de_-20210411-0002.jpg"},{"link":"https:\/\/arb-memes.com\/user\/uploads\/img\/44de_-20210411-0005.jpg"},{"link":"https:\/\/arb-memes.com\/user\/uploads\/img\/amman.lol-20210321-0001.jpg"},{"link":"https:\/\/arb-memes.com\/user\/uploads\/img\/ar.among-20210321-0001.jpg"},{"link":"https:\/\/arb-memes.com\/user\/uploads\/img\/arabmemes0-20210321-0001.jpg"},{"link":"https:\/\/arb-memes.com\/user\/uploads\/img\/az0l.a-20210404-0001.jpg"},{"link":"https:\/\/arb-memes.com\/user\/uploads\/img\/beige__iraqi-20210404-0001.jpg"},{"link":"https:\/\/arb-memes.com\/user\/uploads\/img\/dctj-20210321-0002.jpg"},{"link":"https:\/\/arb-memes.com\/user\/uploads\/img\/dctj-20210401-0002.jpg"},{"link":"https:\/\/arb-memes.com\/user\/uploads\/img\/dctj-20210402-0002.jpg"},{"link":"https:\/\/arb-memes.com\/user\/uploads\/img\/dctj-20210402-0004.jpg"},{"link":"https:\/\/arb-memes.com\/user\/uploads\/img\/dctj-20210404-0003.jpg"},{"link":"https:\/\/arb-memes.com\/user\/uploads\/img\/dctj-20210404-0004.jpg"},{"link":"https:\/\/arb-memes.com\/user\/uploads\/img\/demix7m-20210321-0001.jpg"},{"link":"https:\/\/arb-memes.com\/user\/uploads\/img\/demix7m-20210321-0003.jpg"},{"link":"https:\/\/arb-memes.com\/user\/uploads\/img\/demix7m-20210321-0004.jpg"},{"link":"https:\/\/arb-memes.com\/user\/uploads\/img\/demix7m-20210321-0006.jpg"},{"link":"https:\/\/arb-memes.com\/user\/uploads\/img\/demix7m-20210321-0008.jpg"},{"link":"https:\/\/arb-memes.com\/user\/uploads\/img\/demix7m-20210321-0009.jpg"},{"link":"https:\/\/arb-memes.com\/user\/uploads\/img\/dhf69_-20210404-0003.jpg"},{"link":"https:\/\/arb-memes.com\/user\/uploads\/img\/doctor_komik-20210321-0008.jpg"},{"link":"https:\/\/arb-memes.com\/user\/uploads\/img\/f1vs_-20210321-0001.jpg"},{"link":"https:\/\/arb-memes.com\/user\/uploads\/img\/gff_k-20210321-0001.jpg"},{"link":"https:\/\/arb-memes.com\/user\/uploads\/img\/iheliouz-20210327-0002.jpg"},{"link":"https:\/\/arb-memes.com\/user\/uploads\/img\/IMG_20210327_131440.jpg"},{"link":"https:\/\/arb-memes.com\/user\/uploads\/img\/IMG_20210327_131458.jpg"},{"link":"https:\/\/arb-memes.com\/user\/uploads\/img\/IMG_20210404_191541.jpg"},{"link":"https:\/\/arb-memes.com\/user\/uploads\/img\/IMG_20210404_191553.jpg"},{"link":"https:\/\/arb-memes.com\/user\/uploads\/img\/IMG_20210413_111614.jpg"},{"link":"https:\/\/arb-memes.com\/user\/uploads\/img\/IMG_20210413_111624.jpg"},{"link":"https:\/\/arb-memes.com\/user\/uploads\/img\/IMG_20210413_111652.jpg"},{"link":"https:\/\/arb-memes.com\/user\/uploads\/img\/IMG_20210413_111707.jpg"},{"link":"https:\/\/arb-memes.com\/user\/uploads\/img\/IMG_20210413_111720.jpg"},{"link":"https:\/\/arb-memes.com\/user\/uploads\/img\/IMG_20210413_111743.jpg"},{"link":"https:\/\/arb-memes.com\/user\/uploads\/img\/IMG_20210413_111802.jpg"},{"link":"https:\/\/arb-memes.com\/user\/uploads\/img\/IMG_20210413_111829.jpg"},{"link":"https:\/\/arb-memes.com\/user\/uploads\/img\/IMG_20210413_111918.jpg"},{"link":"https:\/\/arb-memes.com\/user\/uploads\/img\/informations_iq-20210321-0001.jpg"},{"link":"https:\/\/arb-memes.com\/user\/uploads\/img\/iofficialhacker-20210321-0001.jpg"},{"link":"https:\/\/arb-memes.com\/user\/uploads\/img\/irq_trend-20210321-0001.jpg"},{"link":"https:\/\/arb-memes.com\/user\/uploads\/img\/k2bis-20210411-0009.jpg"},{"link":"https:\/\/arb-memes.com\/user\/uploads\/img\/meev.artist-20210321-0001.jpg"},{"link":"https:\/\/arb-memes.com\/user\/uploads\/img\/meev.artist-20210321-0002.jpg"},{"link":"https:\/\/arb-memes.com\/user\/uploads\/img\/meev.artist-20210321-0003.jpg"},{"link":"https:\/\/arb-memes.com\/user\/uploads\/img\/meev.artist-20210321-0004.jpg"},{"link":"https:\/\/arb-memes.com\/user\/uploads\/img\/meev.artist-20210401-0001.jpg"},{"link":"https:\/\/arb-memes.com\/user\/uploads\/img\/meev.artist-20210401-0002.jpg"},{"link":"https:\/\/arb-memes.com\/user\/uploads\/img\/meev.artist-20210402-0001.jpg"},{"link":"https:\/\/arb-memes.com\/user\/uploads\/img\/meev.artist-20210402-0002.jpg"},{"link":"https:\/\/arb-memes.com\/user\/uploads\/img\/meev.artist-20210404-0004.jpg"},{"link":"https:\/\/arb-memes.com\/user\/uploads\/img\/memex.ar-20210321-0001.jpg"},{"link":"https:\/\/arb-memes.com\/user\/uploads\/img\/memex.ar-20210321-0004.jpg"},{"link":"https:\/\/arb-memes.com\/user\/uploads\/img\/mhkm1_-20210321-0001.jpg"},{"link":"https:\/\/arb-memes.com\/user\/uploads\/img\/mhkm1_-20210321-0002.jpg"},{"link":"https:\/\/arb-memes.com\/user\/uploads\/img\/mhkm1_-20210404-0001.jpg"},{"link":"https:\/\/arb-memes.com\/user\/uploads\/img\/nayttw-20210321-0003.jpg"},{"link":"https:\/\/arb-memes.com\/user\/uploads\/img\/nayttw-20210321-0006.jpg"},{"link":"https:\/\/arb-memes.com\/user\/uploads\/img\/nayttw-20210404-0002.jpg"},{"link":"https:\/\/arb-memes.com\/user\/uploads\/img\/nekat_w_hkam_______-20210402-0001.jpg"},{"link":"https:\/\/arb-memes.com\/user\/uploads\/img\/nekat_w_hkam_______-20210411-0001.jpg"},{"link":"https:\/\/arb-memes.com\/user\/uploads\/img\/new_dose_official-20210321-0001.jpg"},{"link":"https:\/\/arb-memes.com\/user\/uploads\/img\/new_dose_official-20210321-0003.jpg"},{"link":"https:\/\/arb-memes.com\/user\/uploads\/img\/new_dose_official-20210404-0001.jpg"},{"link":"https:\/\/arb-memes.com\/user\/uploads\/img\/new_dose_official-20210404-0003.jpg"},{"link":"https:\/\/arb-memes.com\/user\/uploads\/img\/no.way.lb-20210321-0001.jpg"},{"link":"https:\/\/arb-memes.com\/user\/uploads\/img\/panadolsyria-20210404-0001.jpg"},{"link":"https:\/\/arb-memes.com\/user\/uploads\/img\/qqv.a-20210321-0001.jpg"},{"link":"https:\/\/arb-memes.com\/user\/uploads\/img\/reddit.ar-20210321-0002.jpg"},{"link":"https:\/\/arb-memes.com\/user\/uploads\/img\/reddit.ar-20210321-0003.jpg"},{"link":"https:\/\/arb-memes.com\/user\/uploads\/img\/reddit.ar-20210321-0004.jpg"},{"link":"https:\/\/arb-memes.com\/user\/uploads\/img\/reddit.ar-20210321-0005.jpg"},{"link":"https:\/\/arb-memes.com\/user\/uploads\/img\/reddit.ar-20210402-0001.jpg"},{"link":"https:\/\/arb-memes.com\/user\/uploads\/img\/reddit.ar-20210404-0003.jpg"},{"link":"https:\/\/arb-memes.com\/user\/uploads\/img\/reddit.ar-20210411-0002.jpg"},{"link":"https:\/\/arb-memes.com\/user\/uploads\/img\/reddit.ar-20210411-0005.jpg"},{"link":"https:\/\/arb-memes.com\/user\/uploads\/img\/ryzk-20210321-0001.jpg"},{"link":"https:\/\/arb-memes.com\/user\/uploads\/img\/Screenshot_20210330_124647.jpg"},{"link":"https:\/\/arb-memes.com\/user\/uploads\/img\/sponge_b0be-20210404-0001.jpg"},{"link":"https:\/\/arb-memes.com\/user\/uploads\/img\/tdwu-20210402-0001.jpg"},{"link":"https:\/\/arb-memes.com\/user\/uploads\/img\/techno.75-20210321-0001.jpg"},{"link":"https:\/\/arb-memes.com\/user\/uploads\/img\/IMG_20210414_104600.jpg"},{"link":"https:\/\/arb-memes.com\/user\/uploads\/img\/IMG_20210414_104546.jpg"},{"link":"https:\/\/arb-memes.com\/user\/uploads\/img\/IMG_20210414_104616.jpg"},{"link":"https:\/\/arb-memes.com\/user\/uploads\/img\/IMG_20210414_171439.jpg"},{"link":"https:\/\/arb-memes.com\/user\/uploads\/img\/IMG_20210414_171451.jpg"},{"link":"https:\/\/arb-memes.com\/user\/uploads\/img\/reddit.ar-20210414-0004.jpg"},{"link":"https:\/\/arb-memes.com\/user\/uploads\/img\/reddit.ar-20210411-0001.jpg"},{"link":"https:\/\/arb-memes.com\/user\/uploads\/img\/panadolsyria-20210414-0005.jpg"},{"link":"https:\/\/arb-memes.com\/user\/uploads\/img\/no.way.lb-20210414-0001.jpg"},{"link":"https:\/\/arb-memes.com\/user\/uploads\/img\/3al.5afif-20210414-0001.jpg"},{"link":"https:\/\/arb-memes.com\/user\/uploads\/img\/05bt-20210414-0006.jpg"},{"link":"https:\/\/arb-memes.com\/user\/uploads\/img\/dhf69_-20210411-0001.jpg"},{"link":"https:\/\/arb-memes.com\/user\/uploads\/img\/dhf69_-20210411-0002.jpg"},{"link":"https:\/\/arb-memes.com\/user\/uploads\/img\/doctor_komik-20210414-0008.jpg"},{"link":"https:\/\/arb-memes.com\/user\/uploads\/img\/its_aklnaha-20210411-0001.jpg"},{"link":"https:\/\/arb-memes.com\/user\/uploads\/img\/kharbshat__jo-20210414-0001.jpg"},{"link":"https:\/\/arb-memes.com\/user\/uploads\/img\/174287642_259656599240453_2859836789560181580_n.jpg"},{"link":"https:\/\/arb-memes.com\/user\/uploads\/img\/173591207_178879850726004_6600685434791100051_n.jpg"},{"link":"https:\/\/arb-memes.com\/user\/uploads\/img\/IMG_20210417_125636.jpg"},{"link":"https:\/\/arb-memes.com\/user\/uploads\/img\/Screenshot_20210417_135253.jpg"},{"link":"https:\/\/arb-memes.com\/user\/uploads\/img\/IMG_20210419_104607.jpg"},{"link":"https:\/\/arb-memes.com\/user\/uploads\/img\/reddit.ar-20210414-0001.jpg"},{"link":"https:\/\/arb-memes.com\/user\/uploads\/img\/nayttw-20210414-0001.jpg"},{"link":"https:\/\/arb-memes.com\/user\/uploads\/img\/sponge_b0be-20210414-0001.jpg"},{"link":"https:\/\/arb-memes.com\/user\/uploads\/img\/sponge_b0be-20210414-0003.jpg"},{"link":"https:\/\/arb-memes.com\/user\/uploads\/img\/arabmemes0-20210414-0001.jpg"},{"link":"https:\/\/arb-memes.com\/user\/uploads\/img\/7ob_51-20210414-0001.jpg"},{"link":"https:\/\/arb-memes.com\/user\/uploads\/img\/dctj-20210414-0003.jpg"},{"link":"https:\/\/arb-memes.com\/user\/uploads\/img\/winter_season_1-20210414-0001.jpg"},{"link":"https:\/\/arb-memes.com\/user\/uploads\/img\/176046675_183767553568968_4924811962135901245_n.jpg"},{"link":"https:\/\/arb-memes.com\/user\/uploads\/img\/176356575_731909930813165_495552016602612315_n.jpg"},{"link":"https:\/\/arb-memes.com\/user\/uploads\/img\/new_dose_official-20210414-0004.jpg"},{"link":"https:\/\/arb-memes.com\/user\/uploads\/img\/nahfat_7lwe-20210414-0001.jpg"},{"link":"https:\/\/arb-memes.com\/user\/uploads\/img\/mhkm1_-20210414-0001.jpg"},{"link":"https:\/\/arb-memes.com\/user\/uploads\/img\/doctor_komik-20210414-0002.jpg"},{"link":"https:\/\/arb-memes.com\/user\/uploads\/img\/dhf69_-20210414-0001.jpg"},{"link":"https:\/\/arb-memes.com\/user\/uploads\/img\/05bt-20210414-0004.jpg"},{"link":"https:\/\/arb-memes.com\/user\/uploads\/img\/05bt-20210414-0003.jpg"},{"link":"https:\/\/arb-memes.com\/user\/uploads\/img\/05bt-20210414-0002.jpg"},{"link":"https:\/\/arb-memes.com\/user\/uploads\/img\/1bc13040-d4e2-4585-80e1-18e0745c2066.jpg"},{"link":"https:\/\/arb-memes.com\/user\/uploads\/img\/44de_-20210425-0012.jpg"},{"link":"https:\/\/arb-memes.com\/user\/uploads\/img\/44de_-20210425-0013.jpg"},{"link":"https:\/\/arb-memes.com\/user\/uploads\/img\/81e75dd2-b410-45d7-880f-7f0fe2fd30ea.jpg"},{"link":"https:\/\/arb-memes.com\/user\/uploads\/img\/a6a19af5-ce82-4d78-8964-a3de62d9610b.jpg"},{"link":"https:\/\/arb-memes.com\/user\/uploads\/img\/doctor_komik-20210425-0003.jpg"},{"link":"https:\/\/arb-memes.com\/user\/uploads\/img\/doctor_komik-20210425-0004.jpg"},{"link":"https:\/\/arb-memes.com\/user\/uploads\/img\/f87a4f44-875a-48bc-88c6-1417a0dfa4c3.jpg"},{"link":"https:\/\/arb-memes.com\/user\/uploads\/img\/imahbuob-20210425-0001.jpg"},{"link":"https:\/\/arb-memes.com\/user\/uploads\/img\/meev.artist-20210425-0010.jpg"},{"link":"https:\/\/arb-memes.com\/user\/uploads\/img\/meev.artist-20210425-0011.jpg"},{"link":"https:\/\/arb-memes.com\/user\/uploads\/img\/mjhoo1l-20210425-0001.jpg"},{"link":"https:\/\/arb-memes.com\/user\/uploads\/img\/mjhoo1l-20210425-0002.jpg"},{"link":"https:\/\/arb-memes.com\/user\/uploads\/img\/nayttw-20210425-0007.jpg"},{"link":"https:\/\/arb-memes.com\/user\/uploads\/img\/new_dose_official-20210425-0009.jpg"},{"link":"https:\/\/arb-memes.com\/user\/uploads\/img\/panadolsyria-20210425-0003.jpg"},{"link":"https:\/\/arb-memes.com\/user\/uploads\/img\/sz.v-20210425-0001.jpg"},{"link":"https:\/\/arb-memes.com\/user\/uploads\/img\/team_empty-20210425-0005.jpg"},{"link":"https:\/\/arb-memes.com\/user\/uploads\/img\/university_of_baghdad1-20210425-0001.jpg"},{"link":"https:\/\/arb-memes.com\/user\/uploads\/img\/d9a8e37c-58a0-4d23-a670-fd0f1ed22c61.jpg"},{"link":"https:\/\/arb-memes.com\/user\/uploads\/img\/IMG_20210427_124940.jpg"},{"link":"https:\/\/arb-memes.com\/user\/uploads\/img\/IMG_20210427_124914.jpg"},{"link":"https:\/\/arb-memes.com\/user\/uploads\/img\/IMG_20210427_124902.jpg"},{"link":"https:\/\/arb-memes.com\/user\/uploads\/img\/fbef8df4-9574-4a4a-a414-6a19f9d68ff3.jpg"},{"link":"https:\/\/arb-memes.com\/user\/uploads\/img\/c1ffe603-bf12-4f04-87ae-c05c2f1efc88.jpg"},{"link":"https:\/\/arb-memes.com\/user\/uploads\/img\/nayttw-20210425-0006.jpg"},{"link":"https:\/\/arb-memes.com\/user\/uploads\/img\/nayttw-20210425-0003.jpg"},{"link":"https:\/\/arb-memes.com\/user\/uploads\/img\/meev.artist-20210425-0008.jpg"},{"link":"https:\/\/arb-memes.com\/user\/uploads\/img\/meev.artist-20210425-0006.jpg"},{"link":"https:\/\/arb-memes.com\/user\/uploads\/img\/meev.artist-20210425-0004.jpg"},{"link":"https:\/\/arb-memes.com\/user\/uploads\/img\/doctor_komik-20210425-0002.jpg"},{"link":"https:\/\/arb-memes.com\/user\/uploads\/img\/dhf69_-20210425-0003.jpg"},{"link":"https:\/\/arb-memes.com\/user\/uploads\/img\/dhf69_-20210425-0002.jpg"},{"link":"https:\/\/arb-memes.com\/user\/uploads\/img\/dhf69_-20210425-0001.jpg"},{"link":"https:\/\/arb-memes.com\/user\/uploads\/img\/3al.5afif-20210425-0001.jpg"},{"link":"https:\/\/arb-memes.com\/user\/uploads\/img\/team_empty-20210425-0002.jpg"},{"link":"https:\/\/arb-memes.com\/user\/uploads\/img\/nhfatsyrian-20210425-0001.jpg"},{"link":"https:\/\/arb-memes.com\/user\/uploads\/img\/nayttw-20210425-0004.jpg"},{"link":"https:\/\/arb-memes.com\/user\/uploads\/img\/IMG_20210430_145411.jpg"},{"link":"https:\/\/arb-memes.com\/user\/uploads\/img\/IMG_20210430_145350.jpg"},{"link":"https:\/\/arb-memes.com\/user\/uploads\/img\/IMG_20210430_145332.jpg"}]